getsamplesize/__init__.py
getsamplesize/getnmin.py
getsamplesize-0.1.0.dist-info/METADATA
getsamplesize-0.1.0.dist-info/WHEEL
getsamplesize-0.1.0.dist-info/top_level.txt
getsamplesize-0.1.0.dist-info/RECORD
